setup.cfg
setup.py
test/test_authority_json_parsing.py
test/test_client_communication.py
test/test_client_json_parsing.py
test/test_ip_json_parsing.py
test/test_statistic_json_parsing.py
test/test_status_communication.py
test/test_status_json_parsing.py
xiaomirouter/__init__.py
xiaomirouter.egg-info/PKG-INFO
xiaomirouter.egg-info/SOURCES.txt
xiaomirouter.egg-info/dependency_links.txt
xiaomirouter.egg-info/requires.txt
xiaomirouter.egg-info/top_level.txt
xiaomirouter/client/__init__.py
xiaomirouter/client/authority.py
xiaomirouter/client/ip.py
xiaomirouter/client/statistic.py
xiaomirouter/status/__init__.py
xiaomirouter/status/count.py
xiaomirouter/status/cpu.py
xiaomirouter/status/dev.py
xiaomirouter/status/hardware.py
xiaomirouter/status/mem.py
xiaomirouter/status/wan.py