Metadata-Version: 1.1
Name: xiaomirouter
Version: 0.0.1
Summary: Deliver info from Xiaomi Router products.
Home-page: https://github.com/RiRomain/python-xiaomi-router/
Author: RiTomain
Author-email: romain.rinie@googlemail.com
License: MIT
Platform: UNKNOWN
Classifier: License :: OSI Approved :: MIT License
Classifier: Operating System :: OS Independent
Classifier: Programming Language :: Python :: 3
Classifier: Development Status :: 4 - Beta
Classifier: Intended Audience :: Developers
